{
  "tickets": [
    {
      "id": "1",
      "customerId": "2",
      "responsibleId": "1",
      "title": "Принтер",
      "description": "Не печатает принтер",
      "building": "3",
      "cabinet": "201",
      "phone": "89174802421",
      "status": "OPEN"
    },
    {
      "id": "2",
      "customerId": "2",
      "responsibleId": null,
      "title": "Сканер",
      "description": "Не сканирует сканер",
      "building": "3",
      "cabinet": "201",
      "phone": "89174802421",
      "status": "IN_PROGRESS"
    },
    {
      "id": "3",
      "customerId": "3",
      "responsibleId": "1",
      "title": "ЭЦП",
      "description": "Не подписывает ЭЦП",
      "building": "2",
      "cabinet": "202",
      "phone": "89174179443",
      "status": "COMPLETED"
    },
    {
      "id": "4",
      "customerId": "3",
      "responsibleId": "1",
      "title": "ЭЦП",
      "description": "Не подписывает ЭЦП",
      "building": "2",
      "cabinet": "202",
      "phone": "89174179443",
      "status": "REJECTED"
    }
  ],
  "users": [
    {
      "id": "1",
      "username": "admin",
      "password": "123",
      "roles": [
        "ADMIN"
      ],
      "avatar": "https://encrypted-tbn0.gstatic.com/images?q=tbn:ANd9GcTBkJigufyq00dk5hZq_acK0ix6Gq5LMj59Kg&s"
    },
    {
      "id": "2",
      "username": "user",
      "password": "123",
      "roles": [
        "USER"
      ],
      "avatar": "https://encrypted-tbn0.gstatic.com/images?q=tbn:ANd9GcTBkJigufyq00dk5hZq_acK0ix6Gq5LMj59Kg&s"
    }
  ],
  "profile": [
    {
      "id": "1",
      "first": "timur",
      "lastname": "ulbi",
      "age": 20,
      "currency": "RUB",
      "country": "Belarus",
      "city": "Moscow",
      "username": "admin213",
      "avatar": "https://encrypted-tbn0.gstatic.com/images?q=tbn:ANd9GcTBkJigufyq00dk5hZq_acK0ix6Gq5LMj59Kg&s"
    },
    {
      "id": "2",
      "first": "Никита",
      "lastname": "П",
      "age": 19,
      "currency": "RUB",
      "country": "Belarus",
      "city": "Moscow",
      "username": "user213",
      "avatar": "https://encrypted-tbn0.gstatic.com/images?q=tbn:ANd9GcTBkJigufyq00dk5hZq_acK0ix6Gq5LMj59Kg&s"
    }
  ]
}